whocitedme/__init__.py
whocitedme/cli.py
whocitedme/processors/__init__.py
whocitedme/processors/id_matcher.py
whocitedme/processors/top_scholar.py
whocitedme/scrapers/__init__.py
whocitedme/scrapers/author_enricher.py
whocitedme/scrapers/author_info.py
whocitedme/scrapers/citing_papers.py
whocitedme/utils/__init__.py
whocitedme/utils/browser.py
whocitedme/utils/captcha.py
whocitedme-0.1.2.dist-info/licenses/LICENSE
whocitedme-0.1.2.dist-info/METADATA
whocitedme-0.1.2.dist-info/WHEEL
whocitedme-0.1.2.dist-info/entry_points.txt
whocitedme-0.1.2.dist-info/top_level.txt
whocitedme-0.1.2.dist-info/RECORD
