Metadata-Version: 2.4
Name: whocitedme
Version: 0.1.2
Summary: Google Scholar citation analysis tool for identifying high-impact citations, influential authors, and notable peers for grant applications and CV building.
Author-email: Keyan Chen <kychen1012@gmail.com>
Maintainer-email: Keyan Chen <kychen1012@gmail.com>
License: MIT
Project-URL: Homepage, https://github.com/KyanChen/WhoCitedMe
Project-URL: Documentation, https://github.com/KyanChen/WhoCitedMe#readme
Project-URL: Repository, https://github.com/KyanChen/WhoCitedMe
Project-URL: Issues, https://github.com/KyanChen/WhoCitedMe/issues
Project-URL: Changelog, https://github.com/KyanChen/WhoCitedMe/releases
Keywords: google-scholar,citation-analysis,academic,research,scraper,bibliography,citations,scholarly
Classifier: Development Status :: 4 - Beta
Classifier: Environment :: Console
Classifier: Intended Audience :: Science/Research
Classifier: License :: OSI Approved :: MIT License
Classifier: Operating System :: OS Independent
Classifier: Programming Language :: Python :: 3
Classifier: Programming Language :: Python :: 3.8
Classifier: Programming Language :: Python :: 3.9
Classifier: Programming Language :: Python :: 3.10
Classifier: Programming Language :: Python :: 3.11
Classifier: Programming Language :: Python :: 3.12
Classifier: Programming Language :: Python :: 3.13
Classifier: Topic :: Scientific/Engineering
Classifier: Topic :: Text Processing :: General
Classifier: Typing :: Typed
Requires-Python: >=3.8
License-File: LICENSE
Requires-Dist: pandas>=2.0.0
Requires-Dist: selenium>=4.0.0
Requires-Dist: undetected-chromedriver>=3.5.0
Requires-Dist: scholarly>=1.7.0
Provides-Extra: dev
Requires-Dist: pytest>=7.0.0; extra == "dev"
Requires-Dist: pytest-cov>=4.0.0; extra == "dev"
Requires-Dist: black>=23.0.0; extra == "dev"
Requires-Dist: ruff>=0.1.0; extra == "dev"
Requires-Dist: mypy>=1.0.0; extra == "dev"
Requires-Dist: pandas-stubs>=2.0.0; extra == "dev"
Dynamic: license-file
